sdrecommender/__init__.py
sdrecommender/_abcrecommender.py
sdrecommender/classifier_model/__init__.py
sdrecommender/classifier_model/_mlrecommender.py
sdrecommender/collaborative_model/__init__.py
sdrecommender/collaborative_model/_itemitemfilter.py
sdrecommender/collaborative_model/_useritemfilter.py
sdrecommender/content_based_model/__init__.py
sdrecommender/content_based_model/_contentbasedfilter.py
sdrecommender-0.0.2.dist-info/METADATA
sdrecommender-0.0.2.dist-info/WHEEL
sdrecommender-0.0.2.dist-info/top_level.txt
sdrecommender-0.0.2.dist-info/RECORD
