Metadata-Version: 2.1
Name: sdrecommender
Version: 0.0.2
Summary: UNKNOWN
Home-page: UNKNOWN
Author: Vanipra
Author-email: <pranavpathare1111@email.com>
License: UNKNOWN
Keywords: python,recommend,recommender,models,machine learning,similarity
Platform: UNKNOWN
Classifier: Development Status :: 3 - Alpha
Classifier: Programming Language :: Python :: 3
Classifier: Operating System :: MacOS :: MacOS X
Classifier: Operating System :: Microsoft :: Windows
Requires-Python: >=3.6
Requires-Dist: pandas (>=1.0.3)
Requires-Dist: numpy (>=1.20.0)
Requires-Dist: scikit-learn (>=0.24.1)
Requires-Dist: scipy (>=1.6.2)
